MANIFEST.in
README.md
requirements.txt
setup.py
rabbitmq_hub/__init__.py
rabbitmq_hub/connection.py
rabbitmq_hub/exception.py
rabbitmq_hub/hub.py
rabbitmq_hub/logger.py
rabbitmq_hub/pub.py
rabbitmq_hub/rabbit.py
rabbitmq_hub/sub.py
rabbitmq_hub.egg-info/PKG-INFO
rabbitmq_hub.egg-info/SOURCES.txt
rabbitmq_hub.egg-info/dependency_links.txt
rabbitmq_hub.egg-info/not-zip-safe
rabbitmq_hub.egg-info/requires.txt
rabbitmq_hub.egg-info/top_level.txt
tests/__init__.py
tests/rabbitmq.py