Metadata-Version: 1.0
Name: rabbitmq-hub
Version: 1.2.2
Summary: rabbitmq connection manager
Home-page: UNKNOWN
Author: Mageia
Author-email: yzg963@gmail.com
License: Proprietary
Platform: any
